batchify/__init__.py
batchify/batchify.py
batchify/test.py
batchify-0.0.1.dist-info/METADATA
batchify-0.0.1.dist-info/WHEEL
batchify-0.0.1.dist-info/top_level.txt
batchify-0.0.1.dist-info/RECORD
